icraw/__init__.py
icraw/crawler.py
icraw-0.0.2.dist-info/LICENSE
icraw-0.0.2.dist-info/METADATA
icraw-0.0.2.dist-info/WHEEL
icraw-0.0.2.dist-info/top_level.txt
icraw-0.0.2.dist-info/RECORD
