Metadata-Version: 2.1
Name: icraw
Version: 0.0.2
Summary: run_continuously with schedule
Home-page: https://github.com/coghost/icraw
Author: lihe
Author-email: imanux@sina.com
License: GPL
Project-URL: Bug Reports, https://github.com/coghost/icraw/issues
Project-URL: Source, https://github.com/coghost/icraw
Keywords: icraw,izen,profig,logzero
Platform: UNKNOWN
Classifier: Programming Language :: Python :: 3.7
Requires-Python: >=3.7
Requires-Dist: tqdm
Requires-Dist: requests
Requires-Dist: beautifulsoup4
Requires-Dist: logzero
Requires-Dist: ihelp
